danvers/__init__.py
danvers/danvers.py
danvers-1.0.0.dist-info/LICENSE
danvers-1.0.0.dist-info/METADATA
danvers-1.0.0.dist-info/WHEEL
danvers-1.0.0.dist-info/top_level.txt
danvers-1.0.0.dist-info/RECORD
