Metadata-Version: 2.1
Name: danvers
Version: 1.0.0
Summary: Simple, file-based data version control
Home-page: https://github.com/joocer/danvers
Author: Joocer
Author-email: justin.joyce@joocer.com
License: UNKNOWN
Platform: UNKNOWN
